{
  "summary": {
    "protocol": "Unified Fair Comparison",
    "environment": "NonlinearPGG(N=20, Byz=0.3)",
    "hp_grid_size": 4,
    "seeds_per_config": 3,
    "paradigms": {
      "IPPO": {
        "trap_rate": 100.0,
        "total_configs": 4,
        "trapped_configs": 4
      },
      "MAPPO": {
        "trap_rate": 100.0,
        "total_configs": 4,
        "trapped_configs": 4
      },
      "IQL": {
        "trap_rate": 100.0,
        "total_configs": 4,
        "trapped_configs": 4
      },
      "LOLA": {
        "trap_rate": 100.0,
        "total_configs": 4,
        "trapped_configs": 4
      }
    }
  },
  "detailed": {
    "IPPO": {
      "configs": {
        "lr=1e-04_ent=0.01_gam=0.99": {
          "lr": 0.0001,
          "entropy": 0.01,
          "gamma": 0.99,
          "lambda_mean": 0.491,
          "lambda_std": 0.0085,
          "survival_mean": 45.6,
          "welfare_mean": 24.12,
          "trapped": true
        },
        "lr=1e-04_ent=0.1_gam=0.99": {
          "lr": 0.0001,
          "entropy": 0.1,
          "gamma": 0.99,
          "lambda_mean": 0.491,
          "lambda_std": 0.0085,
          "survival_mean": 45.6,
          "welfare_mean": 24.12,
          "trapped": true
        },
        "lr=5e-04_ent=0.01_gam=0.99": {
          "lr": 0.0005,
          "entropy": 0.01,
          "gamma": 0.99,
          "lambda_mean": 0.5036,
          "lambda_std": 0.0388,
          "survival_mean": 52.2,
          "welfare_mean": 24.23,
          "trapped": true
        },
        "lr=5e-04_ent=0.1_gam=0.99": {
          "lr": 0.0005,
          "entropy": 0.1,
          "gamma": 0.99,
          "lambda_mean": 0.5036,
          "lambda_std": 0.0388,
          "survival_mean": 52.2,
          "welfare_mean": 24.23,
          "trapped": true
        }
      },
      "trap_rate": 100.0,
      "total_configs": 4,
      "trapped_configs": 4
    },
    "MAPPO": {
      "configs": {
        "lr=1e-04_ent=0.01_gam=0.99": {
          "lr": 0.0001,
          "entropy": 0.01,
          "gamma": 0.99,
          "lambda_mean": 0.491,
          "lambda_std": 0.0085,
          "survival_mean": 45.6,
          "welfare_mean": 24.12,
          "trapped": true
        },
        "lr=1e-04_ent=0.1_gam=0.99": {
          "lr": 0.0001,
          "entropy": 0.1,
          "gamma": 0.99,
          "lambda_mean": 0.491,
          "lambda_std": 0.0085,
          "survival_mean": 45.6,
          "welfare_mean": 24.12,
          "trapped": true
        },
        "lr=5e-04_ent=0.01_gam=0.99": {
          "lr": 0.0005,
          "entropy": 0.01,
          "gamma": 0.99,
          "lambda_mean": 0.5036,
          "lambda_std": 0.0388,
          "survival_mean": 52.2,
          "welfare_mean": 24.23,
          "trapped": true
        },
        "lr=5e-04_ent=0.1_gam=0.99": {
          "lr": 0.0005,
          "entropy": 0.1,
          "gamma": 0.99,
          "lambda_mean": 0.5036,
          "lambda_std": 0.0388,
          "survival_mean": 52.2,
          "welfare_mean": 24.23,
          "trapped": true
        }
      },
      "trap_rate": 100.0,
      "total_configs": 4,
      "trapped_configs": 4
    },
    "IQL": {
      "configs": {
        "lr=1e-04_ent=0.01_gam=0.99": {
          "lr": 0.0001,
          "entropy": 0.01,
          "gamma": 0.99,
          "lambda_mean": 0.1153,
          "lambda_std": 0.0303,
          "survival_mean": 8.9,
          "welfare_mean": 20.97,
          "trapped": true
        },
        "lr=1e-04_ent=0.1_gam=0.99": {
          "lr": 0.0001,
          "entropy": 0.1,
          "gamma": 0.99,
          "lambda_mean": 0.1153,
          "lambda_std": 0.0303,
          "survival_mean": 8.9,
          "welfare_mean": 20.97,
          "trapped": true
        },
        "lr=5e-04_ent=0.01_gam=0.99": {
          "lr": 0.0005,
          "entropy": 0.01,
          "gamma": 0.99,
          "lambda_mean": 0.1153,
          "lambda_std": 0.0303,
          "survival_mean": 8.9,
          "welfare_mean": 20.97,
          "trapped": true
        },
        "lr=5e-04_ent=0.1_gam=0.99": {
          "lr": 0.0005,
          "entropy": 0.1,
          "gamma": 0.99,
          "lambda_mean": 0.1153,
          "lambda_std": 0.0303,
          "survival_mean": 8.9,
          "welfare_mean": 20.97,
          "trapped": true
        }
      },
      "trap_rate": 100.0,
      "total_configs": 4,
      "trapped_configs": 4
    },
    "LOLA": {
      "configs": {
        "lr=1e-04_ent=0.01_gam=0.99": {
          "lr": 0.0001,
          "entropy": 0.01,
          "gamma": 0.99,
          "lambda_mean": 0.491,
          "lambda_std": 0.0085,
          "survival_mean": 45.6,
          "welfare_mean": 24.12,
          "trapped": true
        },
        "lr=1e-04_ent=0.1_gam=0.99": {
          "lr": 0.0001,
          "entropy": 0.1,
          "gamma": 0.99,
          "lambda_mean": 0.491,
          "lambda_std": 0.0085,
          "survival_mean": 45.6,
          "welfare_mean": 24.12,
          "trapped": true
        },
        "lr=5e-04_ent=0.01_gam=0.99": {
          "lr": 0.0005,
          "entropy": 0.01,
          "gamma": 0.99,
          "lambda_mean": 0.5036,
          "lambda_std": 0.0388,
          "survival_mean": 52.2,
          "welfare_mean": 24.23,
          "trapped": true
        },
        "lr=5e-04_ent=0.1_gam=0.99": {
          "lr": 0.0005,
          "entropy": 0.1,
          "gamma": 0.99,
          "lambda_mean": 0.5036,
          "lambda_std": 0.0388,
          "survival_mean": 52.2,
          "welfare_mean": 24.23,
          "trapped": true
        }
      },
      "trap_rate": 100.0,
      "total_configs": 4,
      "trapped_configs": 4
    }
  }
}